LICENSE
README.md
setup.cfg
setup.py
MICView.egg-info/PKG-INFO
MICView.egg-info/SOURCES.txt
MICView.egg-info/dependency_links.txt
MICView.egg-info/entry_points.txt
MICView.egg-info/requires.txt
MICView.egg-info/top_level.txt
micview/__init__.py
micview/run.py
micview/assets/miclab_logo.jpg
micview/controllers/__init__.py
micview/controllers/hooks/__init__.py
micview/controllers/hooks/image_canvas_hooks.py
micview/controllers/hooks/loading_states_hooks.py
micview/controllers/hooks/optional_states_hooks.py
micview/controllers/hooks/toolframe_states_hooks.py
micview/controllers/services/__init__.py
micview/controllers/services/files/__init__.py
micview/controllers/services/files/file_reader.py
micview/controllers/services/image_viewer/ImageCanvasController.py
micview/controllers/services/image_viewer/ImageFrameController.py
micview/controllers/services/image_viewer/__init__.py
micview/controllers/services/image_viewer/services.py
micview/controllers/services/loading/Animation.py
micview/controllers/services/loading/__init__.py
micview/controllers/services/loading/loader.py
micview/controllers/services/menu/__init__.py
micview/controllers/services/menu/callbacks_onclick.py
micview/controllers/services/screen_size/__init__.py
micview/controllers/services/screen_size/screensize.py
micview/controllers/services/tools/__init__.py
micview/controllers/services/tools/contrast_tool.py
micview/controllers/services/tools/cursor_tool.py
micview/controllers/services/tools/toolframe.py
micview/controllers/services/tools/zoom_tool.py
micview/controllers/services/toplevels/__init__.py
micview/controllers/services/toplevels/input_file_handler.py
micview/controllers/services/volume/__init__.py
micview/controllers/services/volume/controller.py
micview/controllers/services/volume/loader.py
micview/controllers/services/volume/maskPallete.py
micview/controllers/validations/__init__.py
micview/controllers/validations/validate_kwargs.py
micview/controllers/validations/validate_point.py
micview/models/__init__.py
micview/models/getters.py
micview/models/data/__init__.py
micview/models/data/changed_volume_data.py
micview/models/data/cursor_data.py
