Metadata-Version: 2.1
Name: MICView
Version: 1.0.0
Summary: Open-source GUI for visualization of multimodal medical images and segmentations viewing
Home-page: https://github.com/MICLab-Unicamp/micview/archive/refs/tags/v1.0.0.tar.gz
Author: Caio Ruiz Coldebella
Author-email: c232621@dac.unicamp.br
Classifier: Programming Language :: Python :: 3
Classifier: License :: OSI Approved :: MIT License
Classifier: Operating System :: OS Independent
Requires-Python: >=3.8
License-File: LICENSE
